[
    {
        "id": "origin_smp",
        "author": "King Spoons V",
        "url": "//discord.gg/WrTfpt93Cg",
        "thumbnail": "//cdn.discordapp.com/attachments/1096223696902967397/1136384975340589056/origin_smp_banner.png"
    },
    {
        "id": "saste_nashe",
        "author": "Admin",
        "url": "/",
        "thumbnail": "//i.imgur.com/j40cieL.png"
    },
    {
        "id": "rocket_24",
        "author": "Rocket_24",
        "url": "//youtube.com/@rocket_24",
        "thumbnail": "//www.veeforu.com/wp-content/uploads/2022/10/clickbait-thumbnail-template.jpg"
    }
]